<?xml version = '1.0' encoding = 'UTF-8'?>
<TableProxyOraclev20c class="oracle.dbtools.crest.model.design.storage.oracle.v20c.TableProxyOraclev20c" name="rol" directorySegmentName="seg_0" id="3BDD354B-C483-E291-8ABD-430E54226E40">
<createdBy>AO-Alumno</createdBy>
<createdTime>2026-05-07 16:24:26 UTC</createdTime>
<ownerDesignName>ms-pagos</ownerDesignName>
<schemaObject>7A433E60-3200-2D34-1640-7B1AA94D8E35</schemaObject>
<logging>YES</logging>
<partitionedRowMovement>DISABLE</partitionedRowMovement>
<temporaryChanged>false</temporaryChanged>
<accessDriverType>oracle_loader</accessDriverType>
<rejectLimit></rejectLimit>
<columnProxies itemClass="oracle.dbtools.crest.model.design.storage.oracle.v12c.ColumnProxyOraclev12c">
<ColumnProxy name="descripcion" id="4186101B-0F09-D514-C633-DA219CBF7FB2">
<createdBy>AO-Alumno</createdBy>
<createdTime>2026-05-07 16:24:26 UTC</createdTime>
<ownerDesignName>ms-pagos</ownerDesignName>
</ColumnProxy>
<ColumnProxy name="id" id="A6750EF7-39F2-79EB-4DD7-9FF65F7198FE">
<createdBy>AO-Alumno</createdBy>
<createdTime>2026-05-07 16:24:26 UTC</createdTime>
<ownerDesignName>ms-pagos</ownerDesignName>
<autoIncrementDDL>IDENTITY_CLAUSE</autoIncrementDDL>
</ColumnProxy>
<ColumnProxy name="nombre" id="BF2E356A-13D0-5864-C7EE-E9713A2C90D3">
<createdBy>AO-Alumno</createdBy>
<createdTime>2026-05-07 16:24:26 UTC</createdTime>
<ownerDesignName>ms-pagos</ownerDesignName>
</ColumnProxy>
</columnProxies>
<primaryKeys>
<PrimaryKey class="oracle.dbtools.crest.model.design.storage.oracle.v10g.PKProxyOraclev10g" name="pk_rol" id="AA0B04E0-E96B-7E83-C5A4-83805967BED0">
<createdBy>AO-Alumno</createdBy>
<createdTime>2026-05-07 16:24:27 UTC</createdTime>
<ownerDesignName>ms-pagos</ownerDesignName>
<indexSort>SORTED</indexSort>
</PrimaryKey>
</primaryKeys>
<uniqueKeys>
<UniqueKey class="oracle.dbtools.crest.model.design.storage.oracle.v10g.UniqueOraclev10g" name="uq_rol_nombre" id="41784187-9B41-C992-BC0F-1E2EE99D79FA">
<createdBy>AO-Alumno</createdBy>
<createdTime>2026-05-07 16:24:27 UTC</createdTime>
<ownerDesignName>ms-pagos</ownerDesignName>
<indexSort>SORTED</indexSort>
</UniqueKey>
</uniqueKeys>
</TableProxyOraclev20c>
